{"num":"15","SR0":"I-U,S,P","SR1":"J-R,U,Q","SR2":"K-P,S,Q","SR3":"L-S,T,R","SR4":"M-Q,S","SR5":"N-T,S","SR6":"O-P,Q","SR7":"D-M,N,K","SR8":"E-L,J","SR9":"F-J,M,I","SR10":"G-M,K","SR11":"H-N,I,M","SR12":"A-E,G,F","SR13":"B-G,E,F","SR14":"C-E,F,G","firstMem":"P,Q,R,S,T","s1":"R0-H,R1-H,R2-S,R3-H,R4-H,R5-H,R6-H,R7-H,R8-H,R9-H,R10-H,R11-H,R12-H,R13-H,R14-H,M-K","s2":"R0-H,R1-H,R2-P,R3-S,R4-H,R5-H,R6-H,R7-H,R8-H,R9-H,R10-H,R11-H,R12-H,R13-H,R14-H,M-L","s3":"R0-H,R1-H,R2-P,R3-P,R4-S,R5-H,R6-H,R7-H,R8-H,R9-H,R10-H,R11-H,R12-H,R13-H,R14-H,M-M","s4":"R0-H,R1-H,R2-P,R3-P,R4-P,R5-S,R6-H,R7-H,R8-H,R9-H,R10-H,R11-H,R12-H,R13-H,R14-H,M-N","s5":"R0-H,R1-P,R2-P,R3-P,R4-P,R5-P,R6-S,R7-H,R8-H,R9-H,R10-H,R11-H,R12-H,R13-H,R14-H,M-O","s6":"R0-H,R1-H,R2-P,R3-P,R4-P,R5-P,R6-P,R7-S,R8-H,R9-H,R10-H,R11-H,R12-H,R13-H,R14-H,M-D","s7":"R0-H,R1-H,R2-P,R3-P,R4-P,R5-P,R6-P,R7-P,R8-H,R9-H,R10-S,R11-H,R12-H,R13-H,R14-H,M-G","estimate":"100","stepUserCnt":"7"}
