{"s0":{"subGoal":"Высокая з.п.","activeRule":[],"rule":[],"memory":[]},"s1":{"subGoal":"Сфера общения обязывает солидно выглядить","activeRule":[],"rule":[],"memory":[]},"s2":{"subGoal":"Есть возможность купить верхнюю одежду","activeRule":[],"rule":[],"memory":[]},"s3":{"subGoal":"Покупка в меховом салоне","activeRule":[],"rule":[],"memory":[]},"s4":{"subGoal":"Высокая з.п.","activeRule":[],"rule":[],"memory":[]},"s5":{"subGoal":"Сфера общения обязывает солидно выглядить","activeRule":[],"rule":[],"memory":[]},"s6":{"subGoal":"Есть возможность купить верхнюю одежду","activeRule":[],"rule":[],"memory":[]},"s7":{"activeRule":10,"steckGoals":"Сфера общения обязывает солидно выглядить","rule":["H","H","H","H","H","H","H","H","H","H","H","H","S","H","H","H","H","H","H"],"memory":"Есть возможность купить верхнюю одежду"},"s8":{"subGoal":"Есть потребность в верхней одежде","activeRule":[],"rule":[],"memory":[]},"s9":{"activeRule":12,"steckGoals":"Покупка в меховом салоне","rule":["H","H","H","H","H","H","H","H","H","H","H","H","P","H","S","H","H","H","H"],"memory":"Есть потребность в верхней одежде"},"s10":{"activeRule":9,"steckGoals":"Покупка в меховом салоне","rule":["H","H","H","H","H","H","H","H","S","H","H","H","P","H","P","H","H","H","H"],"memory":"Сфера общения обязывает солидно выглядить"},"s11":{"activeRule":12,"steckGoals":"Покупка в меховом салоне","rule":["H","H","H","H","H","H","H","H","H","H","H","H","H","H","S","H","H","H","H"],"memory":[]},"s12":{"activeRule":10,"rule":["H","H","H","H","H","H","H","H","H","H","H","H","S","H","H","H","H","H","H"],"memory":[]},"s13":{"subGoal":"Есть скидки в меховом салоне","activeRule":[],"rule":[],"memory":[]},"s14":{"activeRule":11,"steckGoals":"Покупка в меховом салоне","rule":["H","H","H","H","H","H","H","H","P","H","S","H","P","H","P","H","H","H","H"],"memory":"Есть скидки в меховом салоне"},"s15":{"activeRule":3,"steckGoals":"Покупка в меховом салоне","rule":["H","H","H","H","S","H","H","H","P","H","P","H","P","H","P","H","H","H","H"],"memory":"Высокая з.п."},"s16":{"activeRule":5,"steckGoals":"Покупка в меховом салоне","rule":["H","H","H","H","H","H","S","H","H","H","H","H","H","H","H","H","H","H","H"],"memory":[]},"firstMemory":"Есть желание купить верхнюю одежду,Нет желания купить верхнюю одежду,Погодные условия способствуют покупке,Погодные условия не способствуют покупке"}
