{"s0":{"activeRule":1,"rule":["S","H","H","H","H","H","H","H","H","H","H","H","H","H"],"memory":"лучшее обслуживание"},"s1":{"activeRule":6,"rule":["P","H","H","H","H","S","H","H","H","H","H","H","H","H"],"memory":"быстрая погрузка багажа"},"s2":{"activeRule":1,"rule":["S","H","H","H","H","H","H","H","H","H","H","H","H","H"],"memory":"приятный полет"},"s3":{"activeRule":1,"steckGoals":"приятный полет","rule":["S","H","H","H","H","H","H","H","H","H","H","H","H","H"],"memory":[]},"s4":{"activeRule":5,"rule":["P","H","H","H","H","P","S","H","H","H","H","H","H","H"],"memory":"до аэропорта на спецлимузине"},"s5":{"activeRule":7,"steckGoals":"до аэропорта на спецлимузине","rule":["H","H","H","H","H","H","H","H","H","H","S","H","H","H"],"memory":"Бронь бизнескласса"},"firstMemory":"много денег,удобство,мало денег,нужда,есть багаж"}
