{"s0":{"activeRule":16,"rule":["H","H","H","H","H","H","H","H","H","H","H","H","S","H","H","S"],"memory":[]},"s1":{"activeRule":9,"rule":["H","H","H","H","H","H","H","H","S","S","H","H","H","H","H","H"],"memory":[]},"s2":{"activeRule":3,"rule":["H","H","H","H","S","S","H","H","H","H","H","H","H","H","H","H"],"memory":[]},"s3":{"activeRule":2,"rule":["S","H","H","H","H","H","H","H","H","H","H","H","H","H","H","H"],"memory":[]},"s4":{"activeRule":4,"rule":["H","H","H","S","H","H","H","H","H","H","H","H","H","H","H","H"],"memory":[]},"firstMemory":"Много денег,Долгая поездка,Мало денег,Короткая поездка,Есть багаж,Есть дети"}
